MANIFEST.in
NEWS.txt
README.rst
setup.py
src/commentsauth/__init__.py
src/commentsauth/models.py
src/commentsauth/tests.py
src/commentsauth/urls.py
src/commentsauth/views.py
src/django_contrib_comments_auth.egg-info/PKG-INFO
src/django_contrib_comments_auth.egg-info/SOURCES.txt
src/django_contrib_comments_auth.egg-info/dependency_links.txt
src/django_contrib_comments_auth.egg-info/entry_points.txt
src/django_contrib_comments_auth.egg-info/not-zip-safe
src/django_contrib_comments_auth.egg-info/top_level.txt