Metadata-Version: 1.0
Name: django-contrib-comments-auth
Version: 0.1.1
Summary: This adds authentication to django.contrib.comments.
Home-page: http://www.julianmoritz.de
Author: Julian Moritz
Author-email: jumo@gmx.de
License: BSD
Keywords: comments django web
Platform: UNKNOWN
